{
    "cardSlots": [],
    "powerSupplySlots": [
        {
            "entPhysicalClass": "PowerSupply",
            "tempSensors": [
                {
                    "maxTemperature": 0.0,
                    "maxTemperatureLastChange": 1590495762.0704176,
                    "hwStatus": "ok",
                    "alertCount": 0,
                    "description": "Internal hot spot sensor",
                    "overheatThreshold": 100.0,
                    "criticalThreshold": 105.0,
                    "inAlertState": false,
                    "targetTemperature": 85.0,
                    "relPos": "1",
                    "currentTemperature": 0.0,
                    "setPointTemperature": 83.75,
                    "pidDriverCount": 0,
                    "isPidDriver": false,
                    "name": "TempSensorP1/1"
                },
                {
                    "maxTemperature": 0.0,
                    "maxTemperatureLastChange": 1590495762.07041,
                    "hwStatus": "ok",
                    "alertCount": 0,
                    "description": "Internal ambient sensor",
                    "overheatThreshold": 70.0,
                    "criticalThreshold": 75.0,
                    "inAlertState": false,
                    "targetTemperature": 55.0,
                    "relPos": "2",
                    "currentTemperature": 0.0,
                    "setPointTemperature": 53.75,
                    "pidDriverCount": 0,
                    "isPidDriver": false,
                    "name": "TempSensorP1/2"
                }
            ],
            "relPos": "1"
        },
        {
            "entPhysicalClass": "PowerSupply",
            "tempSensors": [
                {
                    "maxTemperature": 27.0,
                    "maxTemperatureLastChange": 1590486161.4192023,
                    "hwStatus": "ok",
                    "alertCount": 0,
                    "description": "Internal hot spot sensor",
                    "overheatThreshold": 100.0,
                    "criticalThreshold": 105.0,
                    "inAlertState": false,
                    "targetTemperature": 85.0,
                    "relPos": "1",
                    "currentTemperature": 25.0,
                    "setPointTemperature": 83.75,
                    "pidDriverCount": 0,
                    "isPidDriver": false,
                    "name": "TempSensorP2/1"
                },
                {
                    "maxTemperature": 14.0,
                    "maxTemperatureLastChange": 1590486102.1739235,
                    "hwStatus": "ok",
                    "alertCount": 0,
                    "description": "Internal ambient sensor",
                    "overheatThreshold": 70.0,
                    "criticalThreshold": 75.0,
                    "inAlertState": false,
                    "targetTemperature": 55.0,
                    "relPos": "2",
                    "currentTemperature": 12.0,
                    "setPointTemperature": 53.75,
                    "pidDriverCount": 0,
                    "isPidDriver": false,
                    "name": "TempSensorP2/2"
                }
            ],
            "relPos": "2"
        }
    ],
    "shutdownOnOverheat": true,
    "tempSensors": [
        {
            "maxTemperature": 38.0,
            "maxTemperatureLastChange": 1590484768.9363105,
            "hwStatus": "ok",
            "alertCount": 0,
            "description": "Digital Temperature Sensor on cpu0",
            "overheatThreshold": 95.0,
            "criticalThreshold": 105.0,
            "inAlertState": false,
            "targetTemperature": 80.0,
            "relPos": "1",
            "currentTemperature": 34.0,
            "setPointTemperature": 78.75,
            "pidDriverCount": 0,
            "isPidDriver": false,
            "name": "TempSensor1"
        },
        {
            "maxTemperature": 36.0,
            "maxTemperatureLastChange": 1590338514.6076462,
            "hwStatus": "ok",
            "alertCount": 0,
            "description": "Digital Temperature Sensor on cpu1",
            "overheatThreshold": 95.0,
            "criticalThreshold": 105.0,
            "inAlertState": false,
            "targetTemperature": 80.0,
            "relPos": "2",
            "currentTemperature": 31.0,
            "setPointTemperature": 78.75,
            "pidDriverCount": 0,
            "isPidDriver": false,
            "name": "TempSensor2"
        },
        {
            "maxTemperature": 38.0,
            "maxTemperatureLastChange": 1590484768.936512,
            "hwStatus": "ok",
            "alertCount": 0,
            "description": "Digital Temperature Sensor on cpu2",
            "overheatThreshold": 95.0,
            "criticalThreshold": 105.0,
            "inAlertState": false,
            "targetTemperature": 80.0,
            "relPos": "3",
            "currentTemperature": 34.0,
            "setPointTemperature": 78.75,
            "pidDriverCount": 0,
            "isPidDriver": false,
            "name": "TempSensor3"
        },
        {
            "maxTemperature": 36.0,
            "maxTemperatureLastChange": 1590338514.6075017,
            "hwStatus": "ok",
            "alertCount": 0,
            "description": "Digital Temperature Sensor on cpu3",
            "overheatThreshold": 95.0,
            "criticalThreshold": 105.0,
            "inAlertState": false,
            "targetTemperature": 80.0,
            "relPos": "4",
            "currentTemperature": 31.0,
            "setPointTemperature": 78.75,
            "pidDriverCount": 0,
            "isPidDriver": false,
            "name": "TempSensor4"
        },
        {
            "maxTemperature": 28.0,
            "maxTemperatureLastChange": 1590486134.289107,
            "hwStatus": "ok",
            "alertCount": 0,
            "lastPidDriverTime": 1590338454.5211713,
            "description": "Supervisor temp sensor",
            "overheatThreshold": 75.0,
            "criticalThreshold": 85.0,
            "inAlertState": false,
            "targetTemperature": 55.0,
            "relPos": "5",
            "currentTemperature": 26.0,
            "setPointTemperature": 53.75,
            "pidDriverCount": 6,
            "isPidDriver": false,
            "name": "TempSensor5"
        },
        {
            "maxTemperature": 23.875,
            "maxTemperatureLastChange": 1590485861.7540352,
            "hwStatus": "ok",
            "alertCount": 0,
            "description": "Supervisor front-panel temp sensor",
            "overheatThreshold": 75.0,
            "criticalThreshold": 85.0,
            "inAlertState": false,
            "targetTemperature": 55.0,
            "relPos": "6",
            "currentTemperature": 21.75,
            "setPointTemperature": 53.75,
            "pidDriverCount": 0,
            "isPidDriver": false,
            "name": "TempSensor6"
        },
        {
            "maxTemperature": 23.0,
            "maxTemperatureLastChange": 1590486104.6726687,
            "hwStatus": "ok",
            "alertCount": 0,
            "description": "Supervisor back-panel temp sensor",
            "overheatThreshold": 75.0,
            "criticalThreshold": 85.0,
            "inAlertState": false,
            "targetTemperature": 55.0,
            "relPos": "7",
            "currentTemperature": 21.0,
            "setPointTemperature": 53.75,
            "pidDriverCount": 0,
            "isPidDriver": false,
            "name": "TempSensor7"
        },
        {
            "maxTemperature": 30.0,
            "maxTemperatureLastChange": 1590486294.2597594,
            "hwStatus": "ok",
            "alertCount": 0,
            "description": "CPU VRM temp sensor 0",
            "overheatThreshold": 105.0,
            "criticalThreshold": 110.0,
            "inAlertState": false,
            "targetTemperature": 60.0,
            "relPos": "8",
            "currentTemperature": 29.0,
            "setPointTemperature": 58.75,
            "pidDriverCount": 0,
            "isPidDriver": false,
            "name": "TempSensor8"
        },
        {
            "maxTemperature": 30.0,
            "maxTemperatureLastChange": 1590486288.3355255,
            "hwStatus": "ok",
            "alertCount": 0,
            "description": "CPU VRM temp sensor 1",
            "overheatThreshold": 105.0,
            "criticalThreshold": 110.0,
            "inAlertState": false,
            "targetTemperature": 60.0,
            "relPos": "9",
            "currentTemperature": 29.0,
            "setPointTemperature": 58.75,
            "pidDriverCount": 0,
            "isPidDriver": false,
            "name": "TempSensor9"
        },
        {
            "maxTemperature": 24.0,
            "maxTemperatureLastChange": 1590486098.8644934,
            "hwStatus": "ok",
            "alertCount": 0,
            "description": "Upper board sensor",
            "overheatThreshold": 65.0,
            "criticalThreshold": 75.0,
            "inAlertState": false,
            "targetTemperature": 55.0,
            "relPos": "10",
            "currentTemperature": 22.0,
            "setPointTemperature": 53.75,
            "pidDriverCount": 0,
            "isPidDriver": false,
            "name": "TempSensor10"
        },
        {
            "maxTemperature": 22.75,
            "maxTemperatureLastChange": 1590485768.4421666,
            "hwStatus": "ok",
            "alertCount": 0,
            "description": "Upper front-panel temp sensor",
            "overheatThreshold": 65.0,
            "criticalThreshold": 75.0,
            "inAlertState": false,
            "targetTemperature": 55.0,
            "relPos": "11",
            "currentTemperature": 20.5,
            "setPointTemperature": 53.75,
            "pidDriverCount": 0,
            "isPidDriver": false,
            "name": "TempSensor11"
        },
        {
            "maxTemperature": 25.0,
            "maxTemperatureLastChange": 1590486163.4944267,
            "hwStatus": "ok",
            "alertCount": 0,
            "description": "Lower board sensor",
            "overheatThreshold": 65.0,
            "criticalThreshold": 75.0,
            "inAlertState": false,
            "targetTemperature": 55.0,
            "relPos": "12",
            "currentTemperature": 23.0,
            "setPointTemperature": 53.75,
            "pidDriverCount": 0,
            "isPidDriver": false,
            "name": "TempSensor12"
        },
        {
            "maxTemperature": 23.75,
            "maxTemperatureLastChange": 1590485967.9950166,
            "hwStatus": "ok",
            "alertCount": 0,
            "description": "Lower front-panel temp sensor",
            "overheatThreshold": 65.0,
            "criticalThreshold": 75.0,
            "inAlertState": false,
            "targetTemperature": 55.0,
            "relPos": "13",
            "currentTemperature": 21.875,
            "setPointTemperature": 53.75,
            "pidDriverCount": 0,
            "isPidDriver": false,
            "name": "TempSensor13"
        },
        {
            "maxTemperature": 34.659200000000006,
            "maxTemperatureLastChange": 1590485934.8891525,
            "hwStatus": "ok",
            "alertCount": 0,
            "description": "Trident Bottom Right Outer",
            "overheatThreshold": 100.0,
            "criticalThreshold": 120.0,
            "inAlertState": false,
            "targetTemperature": 80.0,
            "relPos": "14",
            "currentTemperature": 32.4896,
            "setPointTemperature": 78.75,
            "pidDriverCount": 0,
            "isPidDriver": false,
            "name": "TempSensor14"
        },
        {
            "maxTemperature": 35.74400000000001,
            "maxTemperatureLastChange": 1590485924.8683565,
            "hwStatus": "ok",
            "alertCount": 0,
            "description": "Trident Bottom Left Outer",
            "overheatThreshold": 100.0,
            "criticalThreshold": 120.0,
            "inAlertState": false,
            "targetTemperature": 80.0,
            "relPos": "15",
            "currentTemperature": 33.574400000000004,
            "setPointTemperature": 78.75,
            "pidDriverCount": 0,
            "isPidDriver": false,
            "name": "TempSensor15"
        },
        {
            "maxTemperature": 34.659200000000006,
            "maxTemperatureLastChange": 1590485909.8582451,
            "hwStatus": "ok",
            "alertCount": 0,
            "description": "Trident Top Left Outer",
            "overheatThreshold": 100.0,
            "criticalThreshold": 120.0,
            "inAlertState": false,
            "targetTemperature": 80.0,
            "relPos": "16",
            "currentTemperature": 32.4896,
            "setPointTemperature": 78.75,
            "pidDriverCount": 0,
            "isPidDriver": false,
            "name": "TempSensor16"
        },
        {
            "maxTemperature": 34.659200000000006,
            "maxTemperatureLastChange": 1590485949.897491,
            "hwStatus": "ok",
            "alertCount": 0,
            "description": "Trident Top Right Outer",
            "overheatThreshold": 100.0,
            "criticalThreshold": 120.0,
            "inAlertState": false,
            "targetTemperature": 80.0,
            "relPos": "17",
            "currentTemperature": 32.4896,
            "setPointTemperature": 78.75,
            "pidDriverCount": 0,
            "isPidDriver": false,
            "name": "TempSensor17"
        },
        {
            "maxTemperature": 35.74400000000001,
            "maxTemperatureLastChange": 1590485974.9224114,
            "hwStatus": "ok",
            "alertCount": 0,
            "description": "Trident Bottom Right Inner",
            "overheatThreshold": 100.0,
            "criticalThreshold": 120.0,
            "inAlertState": false,
            "targetTemperature": 80.0,
            "relPos": "18",
            "currentTemperature": 34.116800000000005,
            "setPointTemperature": 78.75,
            "pidDriverCount": 0,
            "isPidDriver": false,
            "name": "TempSensor18"
        },
        {
            "maxTemperature": 36.8288,
            "maxTemperatureLastChange": 1590485839.8122787,
            "hwStatus": "ok",
            "alertCount": 0,
            "description": "Trident Bottom Left Inner",
            "overheatThreshold": 100.0,
            "criticalThreshold": 120.0,
            "inAlertState": false,
            "targetTemperature": 80.0,
            "relPos": "19",
            "currentTemperature": 34.659200000000006,
            "setPointTemperature": 78.75,
            "pidDriverCount": 0,
            "isPidDriver": false,
            "name": "TempSensor19"
        },
        {
            "maxTemperature": 35.74400000000001,
            "maxTemperatureLastChange": 1590485964.9120567,
            "hwStatus": "ok",
            "alertCount": 0,
            "description": "Trident Top Left Inner",
            "overheatThreshold": 100.0,
            "criticalThreshold": 120.0,
            "inAlertState": false,
            "targetTemperature": 80.0,
            "relPos": "20",
            "currentTemperature": 33.574400000000004,
            "setPointTemperature": 78.75,
            "pidDriverCount": 0,
            "isPidDriver": false,
            "name": "TempSensor20"
        },
        {
            "maxTemperature": 35.201600000000006,
            "maxTemperatureLastChange": 1590485824.803781,
            "hwStatus": "ok",
            "alertCount": 0,
            "description": "Trident Top Right Inner",
            "overheatThreshold": 100.0,
            "criticalThreshold": 120.0,
            "inAlertState": false,
            "targetTemperature": 80.0,
            "relPos": "21",
            "currentTemperature": 33.032000000000004,
            "setPointTemperature": 78.75,
            "pidDriverCount": 0,
            "isPidDriver": false,
            "name": "TempSensor21"
        }
    ],
    "systemStatus": "temperatureOk"
}