{
    "interfaceDescriptions": {
        "Ethernet8": {
            "interfaceStatus": "down",
            "description": "",
            "lineProtocolStatus": "notPresent"
        },
        "Ethernet9": {
            "interfaceStatus": "down",
            "description": "",
            "lineProtocolStatus": "notPresent"
        },
        "Ethernet2": {
            "interfaceStatus": "down",
            "description": "",
            "lineProtocolStatus": "down"
        },
        "Ethernet3": {
            "interfaceStatus": "down",
            "description": "",
            "lineProtocolStatus": "down"
        },
        "Ethernet1": {
            "interfaceStatus": "up",
            "description": "\"switch1 **** Ethernet2\"",
            "lineProtocolStatus": "up"
        },
        "Ethernet6": {
            "interfaceStatus": "down",
            "description": "",
            "lineProtocolStatus": "notPresent"
        },
        "Ethernet7": {
            "interfaceStatus": "down",
            "description": "",
            "lineProtocolStatus": "notPresent"
        },
        "Ethernet4": {
            "interfaceStatus": "down",
            "description": "",
            "lineProtocolStatus": "down"
        },
        "Ethernet5": {
            "interfaceStatus": "down",
            "description": "",
            "lineProtocolStatus": "notPresent"
        },
        "Ethernet22": {
            "interfaceStatus": "down",
            "description": "",
            "lineProtocolStatus": "notPresent"
        },
        "Ethernet50": {
            "interfaceStatus": "down",
            "description": "",
            "lineProtocolStatus": "down"
        },
        "Ethernet51": {
            "interfaceStatus": "down",
            "description": "",
            "lineProtocolStatus": "down"
        },
        "Ethernet52": {
            "interfaceStatus": "down",
            "description": "",
            "lineProtocolStatus": "down"
        },
        "Ethernet38": {
            "interfaceStatus": "down",
            "description": "",
            "lineProtocolStatus": "notPresent"
        },
        "Ethernet39": {
            "interfaceStatus": "down",
            "description": "",
            "lineProtocolStatus": "notPresent"
        },
        "Ethernet18": {
            "interfaceStatus": "down",
            "description": "",
            "lineProtocolStatus": "notPresent"
        },
        "Ethernet19": {
            "interfaceStatus": "down",
            "description": "",
            "lineProtocolStatus": "notPresent"
        },
        "Ethernet32": {
            "interfaceStatus": "down",
            "description": "",
            "lineProtocolStatus": "notPresent"
        },
        "Ethernet15": {
            "interfaceStatus": "down",
            "description": "",
            "lineProtocolStatus": "notPresent"
        },
        "Ethernet16": {
            "interfaceStatus": "down",
            "description": "",
            "lineProtocolStatus": "notPresent"
        },
        "Ethernet31": {
            "interfaceStatus": "down",
            "description": "",
            "lineProtocolStatus": "notPresent"
        },
        "Ethernet10": {
            "interfaceStatus": "down",
            "description": "",
            "lineProtocolStatus": "notPresent"
        },
        "Ethernet37": {
            "interfaceStatus": "down",
            "description": "",
            "lineProtocolStatus": "notPresent"
        },
        "Ethernet34": {
            "interfaceStatus": "down",
            "description": "",
            "lineProtocolStatus": "notPresent"
        },
        "Ethernet35": {
            "interfaceStatus": "down",
            "description": "",
            "lineProtocolStatus": "notPresent"
        },
        "Ethernet14": {
            "interfaceStatus": "down",
            "description": "",
            "lineProtocolStatus": "notPresent"
        },
        "Loopback0": {
            "interfaceStatus": "up",
            "description": "",
            "lineProtocolStatus": "up"
        },
        "Ethernet33": {
            "interfaceStatus": "down",
            "description": "",
            "lineProtocolStatus": "notPresent"
        },
        "Ethernet30": {
            "interfaceStatus": "down",
            "description": "",
            "lineProtocolStatus": "notPresent"
        },
        "Management1": {
            "interfaceStatus": "up",
            "description": "",
            "lineProtocolStatus": "up"
        },
        "Ethernet17": {
            "interfaceStatus": "down",
            "description": "",
            "lineProtocolStatus": "notPresent"
        },
        "Ethernet49": {
            "interfaceStatus": "down",
            "description": "",
            "lineProtocolStatus": "down"
        },
        "Ethernet48": {
            "interfaceStatus": "down",
            "description": "",
            "lineProtocolStatus": "notPresent"
        },
        "Ethernet47": {
            "interfaceStatus": "down",
            "description": "",
            "lineProtocolStatus": "notPresent"
        },
        "Ethernet36": {
            "interfaceStatus": "down",
            "description": "",
            "lineProtocolStatus": "notPresent"
        },
        "Ethernet45": {
            "interfaceStatus": "down",
            "description": "",
            "lineProtocolStatus": "notPresent"
        },
        "Ethernet44": {
            "interfaceStatus": "down",
            "description": "",
            "lineProtocolStatus": "notPresent"
        },
        "Ethernet43": {
            "interfaceStatus": "down",
            "description": "",
            "lineProtocolStatus": "notPresent"
        },
        "Ethernet42": {
            "interfaceStatus": "down",
            "description": "",
            "lineProtocolStatus": "notPresent"
        },
        "Ethernet41": {
            "interfaceStatus": "down",
            "description": "",
            "lineProtocolStatus": "notPresent"
        },
        "Ethernet40": {
            "interfaceStatus": "down",
            "description": "",
            "lineProtocolStatus": "notPresent"
        },
        "Ethernet29": {
            "interfaceStatus": "down",
            "description": "",
            "lineProtocolStatus": "notPresent"
        },
        "Ethernet28": {
            "interfaceStatus": "down",
            "description": "",
            "lineProtocolStatus": "notPresent"
        },
        "Ethernet11": {
            "interfaceStatus": "down",
            "description": "",
            "lineProtocolStatus": "notPresent"
        },
        "Ethernet12": {
            "interfaceStatus": "down",
            "description": "",
            "lineProtocolStatus": "notPresent"
        },
        "Ethernet46": {
            "interfaceStatus": "down",
            "description": "",
            "lineProtocolStatus": "notPresent"
        },
        "Ethernet21": {
            "interfaceStatus": "down",
            "description": "",
            "lineProtocolStatus": "notPresent"
        },
        "Ethernet20": {
            "interfaceStatus": "down",
            "description": "",
            "lineProtocolStatus": "notPresent"
        },
        "Ethernet23": {
            "interfaceStatus": "down",
            "description": "",
            "lineProtocolStatus": "notPresent"
        },
        "Ethernet13": {
            "interfaceStatus": "down",
            "description": "",
            "lineProtocolStatus": "notPresent"
        },
        "Ethernet25": {
            "interfaceStatus": "down",
            "description": "",
            "lineProtocolStatus": "notPresent"
        },
        "Ethernet24": {
            "interfaceStatus": "up",
            "description": "\"switch2 **** Ethernet24\"",
            "lineProtocolStatus": "up"
        },
        "Ethernet27": {
            "interfaceStatus": "down",
            "description": "",
            "lineProtocolStatus": "notPresent"
        },
        "Ethernet26": {
            "interfaceStatus": "down",
            "description": "",
            "lineProtocolStatus": "notPresent"
        }
    }
}